claves/__init__.py
claves/__main__.py
claves/manager.py
claves/provider.py
claves/utils.py
claves/data/enclave.yaml
claves-1.0a4.data/scripts/claves
claves-1.0a4.dist-info/LICENSE
claves-1.0a4.dist-info/METADATA
claves-1.0a4.dist-info/WHEEL
claves-1.0a4.dist-info/top_level.txt
claves-1.0a4.dist-info/RECORD
