Metadata-Version: 2.1
Name: claves
Version: 1.0a4
Summary: Manage your code enclaves on AWS.
Home-page: https://github.com/varseand/claves
Author: Krzysztof Katowicz-Kowalewski
Author-email: vnd@vndh.net
License: UNKNOWN
Platform: UNKNOWN
Classifier: Development Status :: 3 - Alpha
Classifier: Environment :: Console
Classifier: Intended Audience :: Developers
Classifier: License :: OSI Approved :: MIT License
Classifier: Natural Language :: English
Classifier: Operating System :: MacOS
Classifier: Operating System :: POSIX
Classifier: Programming Language :: Python :: 3
Classifier: Topic :: Security
Classifier: Topic :: Software Development :: Build Tools
Requires-Python: >=3.6
Requires-Dist: boto3
Requires-Dist: PyYAML
